pyForMetrix/__init__.py
pyForMetrix/metrix.py
pyForMetrix/normalizer.py
pyForMetrix/metricCalculators/__init__.py
pyForMetrix/metricCalculators/publications.py
pyForMetrix/metricCalculators/types.py
pyForMetrix/metricCalculators/lidRmetrics/HOME.py
pyForMetrix/metricCalculators/lidRmetrics/Lmoments.py
pyForMetrix/metricCalculators/lidRmetrics/__init__.py
pyForMetrix/metricCalculators/lidRmetrics/basic.py
pyForMetrix/metricCalculators/lidRmetrics/canopydensity.py
pyForMetrix/metricCalculators/lidRmetrics/dispersion.py
pyForMetrix/metricCalculators/lidRmetrics/echo.py
pyForMetrix/metricCalculators/lidRmetrics/interval.py
pyForMetrix/metricCalculators/lidRmetrics/kde.py
pyForMetrix/metricCalculators/lidRmetrics/lad.py
pyForMetrix/metricCalculators/lidRmetrics/percabove.py
pyForMetrix/metricCalculators/lidRmetrics/percentiles.py
pyForMetrix/metricCalculators/lidRmetrics/rumple.py
pyForMetrix/metricCalculators/lidRmetrics/voxels.py
pyForMetrix/utils/__init__.py
pyForMetrix/utils/rasterizer.py
pyForMetrix/utils/voxelizer.py
pyformetrix-0.0.7.dist-info/METADATA
pyformetrix-0.0.7.dist-info/WHEEL
pyformetrix-0.0.7.dist-info/licenses/LICENSE
pyformetrix-0.0.7.dist-info/RECORD
