Metadata-Version: 2.1
Name: pyForMetrix
Version: 0.0.7
Project-URL: Homepage, https://github.com/lwiniwar/pyForMetrix
Project-URL: Bug Tracker, https://github.com/lwiniwar/pyForMetrix/issues
Author-email: Lukas Winiwarter <lukas.pypi@winiwarter.dev>
License-File: LICENSE
Classifier: License :: OSI Approved :: MIT License
Classifier: Operating System :: OS Independent
Classifier: Programming Language :: Python :: 3
Requires-Python: >=3.8
Requires-Dist: deprecated
Requires-Dist: laspy
Requires-Dist: laxpy
Requires-Dist: lmoments3
Requires-Dist: matplotlib
Requires-Dist: numpy
Requires-Dist: pandas
Requires-Dist: pip>=19.3
Requires-Dist: scipy
Requires-Dist: shapely
Requires-Dist: tqdm
Requires-Dist: xarray
